odoo/addons/report_csv/README.rst
odoo/addons/report_csv/__init__.py
odoo/addons/report_csv/__manifest__.py
odoo/addons/report_csv/controllers/__init__.py
odoo/addons/report_csv/controllers/main.py
odoo/addons/report_csv/demo/report.xml
odoo/addons/report_csv/i18n/report_csv.pot
odoo/addons/report_csv/models/__init__.py
odoo/addons/report_csv/models/ir_report.py
odoo/addons/report_csv/report/__init__.py
odoo/addons/report_csv/report/report_csv.py
odoo/addons/report_csv/report/report_partner_csv.py
odoo/addons/report_csv/static/description/icon.png
odoo/addons/report_csv/static/src/js/report/qwebactionmanager.js
odoo/addons/report_csv/tests/__init__.py
odoo/addons/report_csv/tests/test_report.py
odoo/addons/report_csv/views/webclient_templates.xml
odoo11_addon_report_csv-11.0.1.0.0.99.dev4.dist-info/METADATA
odoo11_addon_report_csv-11.0.1.0.0.99.dev4.dist-info/RECORD
odoo11_addon_report_csv-11.0.1.0.0.99.dev4.dist-info/WHEEL
odoo11_addon_report_csv-11.0.1.0.0.99.dev4.dist-info/top_level.txt
